__init__.py
mcp_server.py
domains/__init__.py
domains/reaper_dataclasses.py
tools/__init__.py
tools/rpp_finder.py
tools/rpp_parser.py
mseep_reaper_mcp_server-0.1.5.dist-info/METADATA
mseep_reaper_mcp_server-0.1.5.dist-info/WHEEL
mseep_reaper_mcp_server-0.1.5.dist-info/top_level.txt
mseep_reaper_mcp_server-0.1.5.dist-info/RECORD
